{
    "data": [
      {
        "id": 6302829087749,
        "name": "Economy - Tabulering",
        "notes": "",
        "assignee": {
          "id": 6191220583679,
          "name": "Dennis Haney"
        },
        "completed": false,
        "due_on": null,
        "tags": [
          {
            "id": 6302829087745,
            "name": "Bug"
          },
          {
            "id": 6302829087747,
            "name": "Catglobe"
          }
        ]
      },
      {
        "id": 6302829087737,
        "name": "Copy User functionality",
        "notes": "",
        "assignee": {
          "id": 6191220583679,
          "name": "Dennis Haney"
        },
        "completed": true,
        "due_on": null,
        "tags": [
          {
            "id": 6302829087745,
            "name": "Bug"
          }
        ]
      },
      {
        "id": 6314903320032,
        "name": "test",
        "notes": "http://cg.catglobe.com/SecurityModule/QuickTimeRegistration.aspx?rt=30&id=730\n\nblablabla",
        "assignee": {
          "id": 6191220583679,
          "name": "Dennis Haney"
        },
        "completed": false,
        "due_on": "2025-01-31",
        "tags": []
      },
      {
        "id": 6314903320034,
        "name": "test2",
        "notes": "Hello world",
        "assignee": {
          "id": 6191220583679,
          "name": "Dennis Haney"
        },
        "completed": false,
        "due_on": "2000-01-31",
        "tags": []
      }
    ]
  }